sphinx_basic_ng/__init__.py
sphinx_basic_ng/theme/basic-ng/defindex.html
sphinx_basic_ng/theme/basic-ng/domainindex.html
sphinx_basic_ng/theme/basic-ng/genindex-single.html
sphinx_basic_ng/theme/basic-ng/genindex-split.html
sphinx_basic_ng/theme/basic-ng/genindex.html
sphinx_basic_ng/theme/basic-ng/globaltoc.html
sphinx_basic_ng/theme/basic-ng/layout.html
sphinx_basic_ng/theme/basic-ng/localtoc.html
sphinx_basic_ng/theme/basic-ng/page.html
sphinx_basic_ng/theme/basic-ng/relations.html
sphinx_basic_ng/theme/basic-ng/search.html
sphinx_basic_ng/theme/basic-ng/searchbox.html
sphinx_basic_ng/theme/basic-ng/sourcelink.html
sphinx_basic_ng/theme/basic-ng/theme.conf
sphinx_basic_ng/theme/basic-ng/changes/frameset.html
sphinx_basic_ng/theme/basic-ng/changes/rstsource.html
sphinx_basic_ng/theme/basic-ng/changes/versionchanges.html
sphinx_basic_ng/theme/basic-ng/components/breadcrumbs.html
sphinx_basic_ng/theme/basic-ng/components/edit-this-page.html
sphinx_basic_ng/theme/basic-ng/components/ethical-ads.html
sphinx_basic_ng/theme/basic-ng/components/logo.html
sphinx_basic_ng/theme/basic-ng/components/related-pages.html
sphinx_basic_ng/theme/basic-ng/components/search-hide.html
sphinx_basic_ng/theme/basic-ng/components/search-input.html
sphinx_basic_ng/theme/basic-ng/components/toggle-sidebar-primary.html
sphinx_basic_ng/theme/basic-ng/components/toggle-sidebar-secondary.html
sphinx_basic_ng/theme/basic-ng/components/view-this-page.html
sphinx_basic_ng/theme/basic-ng/sections/announcement.html
sphinx_basic_ng/theme/basic-ng/sections/article.html
sphinx_basic_ng/theme/basic-ng/sections/footer-article.html
sphinx_basic_ng/theme/basic-ng/sections/footer-content.html
sphinx_basic_ng/theme/basic-ng/sections/footer.html
sphinx_basic_ng/theme/basic-ng/sections/header-article.html
sphinx_basic_ng/theme/basic-ng/sections/header-content.html
sphinx_basic_ng/theme/basic-ng/sections/header-secondary.html
sphinx_basic_ng/theme/basic-ng/sections/header.html
sphinx_basic_ng-1.0.0b1.dist-info/LICENSE
sphinx_basic_ng-1.0.0b1.dist-info/METADATA
sphinx_basic_ng-1.0.0b1.dist-info/WHEEL
sphinx_basic_ng-1.0.0b1.dist-info/entry_points.txt
sphinx_basic_ng-1.0.0b1.dist-info/top_level.txt
sphinx_basic_ng-1.0.0b1.dist-info/RECORD
