Metadata-Version: 2.1
Name: sphinx_basic_ng
Version: 1.0.0b1
Summary: A modern skeleton for Sphinx themes.
Home-page: https://github.com/pradyunsg/sphinx-basic-ng
Author: Pradyun Gedam
Author-email: mail@pradyunsg.me
Project-URL: Documentation, https://rtfd.io/sphinx-basic-ng/
Classifier: Framework :: Sphinx
Classifier: Framework :: Sphinx :: Theme
Classifier: License :: OSI Approved :: MIT License
Classifier: Environment :: Web Environment
Classifier: Intended Audience :: Developers
Classifier: Programming Language :: Python :: 3
Classifier: Operating System :: OS Independent
Classifier: Topic :: Documentation
Classifier: Topic :: Software Development :: Documentation
Requires-Python: >=3.7
Provides-Extra: docs
License-File: LICENSE
